psqlgraph/__init__.py
psqlgraph/__main__.py
psqlgraph/attributes.py
psqlgraph/base.py
psqlgraph/edge.py
psqlgraph/exc.py
psqlgraph/hooks.py
psqlgraph/mocks.py
psqlgraph/node.py
psqlgraph/psql.py
psqlgraph/query.py
psqlgraph/session.py
psqlgraph/util.py
psqlgraph/voided_edge.py
psqlgraph/voided_node.py
psqlgraph-3.2.0.dist-info/METADATA
psqlgraph-3.2.0.dist-info/WHEEL
psqlgraph-3.2.0.dist-info/licenses/LICENSE
psqlgraph-3.2.0.dist-info/licenses/NOTICE
psqlgraph-3.2.0.dist-info/RECORD
