Metadata-Version: 2.4
Name: psqlgraph
Version: 3.2.0
Summary: 
License: Apache-2.0
License-File: LICENSE
License-File: NOTICE
Author: CTDS UChicago
Author-email: cdis@uchicago.edu
Requires-Python: >=3.13,<4
Classifier: License :: OSI Approved :: Apache Software License
Classifier: Programming Language :: Python :: 3
Classifier: Programming Language :: Python :: 3.13
Classifier: Programming Language :: Python :: 3.14
Provides-Extra: ipython
Requires-Dist: ipython ; extra == "ipython"
Requires-Dist: psycopg2-binary (>=2.8.2,<3)
Requires-Dist: rstr (>=2.2.6)
Requires-Dist: six (>=1.12.0)
Requires-Dist: sqlalchemy (>=1.3.3,<2)
Requires-Dist: xlocal (==0.5)
Project-URL: Homepage, https://gen3.org/
Project-URL: Repository, https://github.com/uc-cdis/gen3datamodel
